futurama/__init__.py
futurama/__main__.py
futurama/quotes.py
futurama-0.1.2.dist-info/METADATA
futurama-0.1.2.dist-info/WHEEL
futurama-0.1.2.dist-info/entry_points.txt
futurama-0.1.2.dist-info/RECORD
