Metadata-Version: 2.1
Name: futurama
Version: 0.1.2
Summary: Random Futurama Quotes
Home-page: https://git.decapod.one/brethil/futurama
Author: brethil
Author-email: bretello@distruzione.org
Requires-Python: >=3.7,<4.0
Classifier: Programming Language :: Python :: 3
Classifier: Programming Language :: Python :: 3.7
Classifier: Programming Language :: Python :: 3.8
Classifier: Programming Language :: Python :: 3.9
Classifier: Programming Language :: Python :: 3.10
Classifier: Programming Language :: Python :: 3.11
Classifier: Programming Language :: Python :: 3.12
